cvprocessor/__init__.py
cvprocessor/authors.py
cvprocessor/cv.py
cvprocessor/education.py
cvprocessor/experience.py
cvprocessor/grants_awards.py
cvprocessor/institutes.py
cvprocessor/intro.py
cvprocessor/memberships.py
cvprocessor/news.py
cvprocessor/presentations.py
cvprocessor/publications.py
cvprocessor/references.py
cvprocessor/research_interests.py
cvprocessor/service.py
cvprocessor/skills.py
cvprocessor/software.py
cvprocessor/supervision.py
cvprocessor/teaching.py
cvprocessor/contact/__init__.py
cvprocessor/contact/contact.py
cvprocessor/date/__init__.py
cvprocessor/date/date.py
cvprocessor/links/__init__.py
cvprocessor/links/links.py
cvprocessor/name/__init__.py
cvprocessor/name/name.py
cvprocessor/personal/__init__.py
cvprocessor/personal/personal.py
cvprocessor/security/__init__.py
cvprocessor/security/security.py
cvprocessor-1.0.8.dist-info/licenses/LICENSE
cvprocessor-1.0.8.dist-info/METADATA
cvprocessor-1.0.8.dist-info/WHEEL
cvprocessor-1.0.8.dist-info/top_level.txt
cvprocessor-1.0.8.dist-info/RECORD
