Metadata-Version: 2.4
Name: cvprocessor
Version: 1.0.8
Summary: CVProcessor is a Python library for processing CV (Curriculum Vitae) or resume documents.
Author-email: "F. Fernando Jurado-Lasso" <fdo.jurado@gmail.com>
License-Expression: MIT
Project-URL: Homepage, https://github.com/fdojurado/CVProcessor
Project-URL: Issues, https://github.com/fdojurado/CVProcessor/issues
Keywords: CV,Curriculum Vitae,Resume,xslx
Classifier: Programming Language :: Python :: 3
Classifier: Operating System :: OS Independent
Requires-Python: >=3.8
License-File: LICENSE
Requires-Dist: pandas
Dynamic: license-file
